{
  "id": "mission_values_grid",
  "type": "SharedSlice",
  "name": "MissionValuesGrid",
  "variations": [
    {
      "id": "default",
      "name": "Default",
      "description": "Default",
      "imageUrl": "",
      "docURL": "...",
      "version": "initial",
      "primary": {
        "items": {
          "type": "Group",
          "config": {
            "label": "items",
            "repeat": true,
            "fields": {
              "title": {
                "type": "Text",
                "config": {
                  "label": "title",
                  "placeholder": ""
                }
              },
              "text": {
                "type": "Text",
                "config": {
                  "label": "text",
                  "placeholder": ""
                }
              },
              "icon": {
                "type": "Text",
                "config": {
                  "label": "icon",
                  "placeholder": ""
                }
              }
            }
          }
        }
      }
    }
  ],
  "description": "MissionValuesGrid"
}